odoo/addons/l10n_nl_kvk_partner/README.rst
odoo/addons/l10n_nl_kvk_partner/__init__.py
odoo/addons/l10n_nl_kvk_partner/__manifest__.py
odoo/addons/l10n_nl_kvk_partner/i18n/l10n_nl_kvk_partner.pot
odoo/addons/l10n_nl_kvk_partner/models/__init__.py
odoo/addons/l10n_nl_kvk_partner/models/res_partner.py
odoo/addons/l10n_nl_kvk_partner/readme/CONTRIBUTORS.md
odoo/addons/l10n_nl_kvk_partner/readme/DESCRIPTION.md
odoo/addons/l10n_nl_kvk_partner/readme/USAGE.md
odoo/addons/l10n_nl_kvk_partner/static/description/icon.png
odoo/addons/l10n_nl_kvk_partner/static/description/index.html
odoo/addons/l10n_nl_kvk_partner/static/img/l10n_nl_kvk_partner.png
odoo/addons/l10n_nl_kvk_partner/tests/__init__.py
odoo/addons/l10n_nl_kvk_partner/tests/test_l10n_nl_kvk_partner.py
odoo/addons/l10n_nl_kvk_partner/views/res_partner_views.xml
odoo_addon_l10n_nl_kvk_partner-18.0.1.0.0.2.dist-info/METADATA
odoo_addon_l10n_nl_kvk_partner-18.0.1.0.0.2.dist-info/WHEEL
odoo_addon_l10n_nl_kvk_partner-18.0.1.0.0.2.dist-info/top_level.txt
odoo_addon_l10n_nl_kvk_partner-18.0.1.0.0.2.dist-info/RECORD
