Metadata-Version: 2.1
Name: odoo-addon-l10n_nl_kvk_partner
Version: 18.0.1.0.0.2
Requires-Python: >=3.10
Requires-Dist: odoo==18.0.*
Summary: Use the Peppol Endpoint as the Dutch Chamber of Commerce number
Home-page: https://github.com/OCA/l10n-netherlands
License: LGPL-3
Author: 360ERP, Odoo Community Association (OCA)
Author-email: support@odoo-community.org
Classifier: Programming Language :: Python
Classifier: Framework :: Odoo
Classifier: Framework :: Odoo :: 18.0
Classifier: License :: OSI Approved :: GNU Lesser General Public License v3 (LGPLv3)
